Modules/SerialTranceiver/SerialTrasceiver/SerialTrasceiver.srcs/sources_1/new/SerialTrasceiver.sv
`timescale 1ns / 1ps

//functioneasa ca un PISO(Parallel Input Serial Output)
module SerialTrasceiver
#(parameter SIZE = 32)
(DataIn, Sample, StartTx, TxDone, Reset, Clk, ClkTx, TxBusy, Dout);
    input [SIZE - 1:0] DataIn;
    input Sample;
    input StartTx;
    input Reset;
    input Clk;
    input ClkTx;
    output reg TxDone;
    output reg TxBusy;
    output reg Dout;
    
    reg [SIZE -1: 0] InternRegister;
    reg [SIZE -1: 0] Count_bits;
    reg TxBusyIntern;
    
    task ResetValues();
        TxBusy <= 1'b0;
        TxBusyIntern <= 1'b0;
        InternRegister <= 32'h0;
        Count_bits <= 32'h0;
        Dout <= 1'b0;
    endtask
    
    always @(posedge Clk or posedge Reset) begin
        if(Reset) begin
            ResetValues();
        end
        else begin
            //in this case we are saving the DataIn inside the intern register
            if(Sample && !StartTx) begin
                if(!TxBusyIntern) begin
                    InternRegister <= DataIn;
                end
                else begin
                    InternRegister <= InternRegister;
                end
            end
            else if(!Sample && StartTx) begin
                if(!TxDone) begin
                    TxBusyIntern <= 1;
                end
                else begin
                    TxBusyIntern <= 0;
                end
            end
            else if(Sample && StartTx) begin
                $display("This case is not possible");
            end
            
            if(Count_bits == (SIZE + 1)) begin
                TxDone <= 1'b1;
                TxBusyIntern <= 1'b0;
                Dout <= 1'b0;
                Count_bits <= 0;
            end
            else begin
                TxDone <= 1'b0;
            end
        end
    end 
    
    always @(posedge ClkTx or posedge Reset) begin
        if(Reset) begin
            ResetValues();
        end
        else begin
          //in this case we will start to sent data to output, bit by bit
          if (Count_bits <= SIZE) begin
                if(TxBusyIntern) begin
                    TxBusy <= 1'b1;
                    Dout <= InternRegister[SIZE -1];
                    InternRegister <= InternRegister << 1;
                    Count_bits++;
                end
          end
          if(Count_bits == (SIZE + 1)) begin
                TxBusy <= 1'b0;
          end
        end
    end
endmodule

module tb_SerialTransciever();
    reg[31:0] DataIn;
    reg Sample;
    reg StartTx;
    reg Reset;
    reg Clk;
    reg ClkTx;
    wire TxDone;
    wire TxBusy;
    wire Dout;
    
    SerialTrasceiver dut
    (.DataIn(DataIn), 
     .Sample(Sample), 
     .StartTx(StartTx), 
     .Reset(Reset), 
     .Clk(Clk),
     .ClkTx(ClkTx),
     .TxDone(TxDone),
     .TxBusy(TxBusy),
     .Dout(Dout)
     );
     
     initial begin
        Sample <= 1'b0;
        StartTx <= 1'b0;
        Clk <= 1'b0;      
        ClkTx <= 1'b0;
     end
     
     always #5 Clk = ~Clk;
     always #15 ClkTx = ~ClkTx;
     
     
     initial begin
        //the first case is when we want to reset the values
        Reset = 1'b1;
        #8
        Reset = 1'b0;
        
        //other scenario is when we want to save the DataIn in the intern register
        #10;
        DataIn = 32'hFF_22_33_45;
        Sample = 1'b1;
        
        //after that we want to send the data to the serial output
        #20;
        Sample = 1'b0;
        StartTx = 1'b1;
        
        #50;
        StartTx = 1'b0;
        
        //let's try the case when TxBusy = 1 and we set Sample = 1
        #20;
        DataIn = 32'h21_11;
        Sample = 1'b1;
        #10; 
        Sample = 1'b0;  
  		//we want to test the case when we want to Reset the values when a transfer is in proces
  		#500;
  		Reset = 1'b1;
  		#13;
  		Reset = 1'b0;
       
        //now we want to make a whole trasnfer to be proceded
       DataIn = 32'hF2_59_FD_1B;
       #10;
       Sample = 1'b1;
       #12;
       Sample = 1'b0;
       #5;
       StartTx = 1'b1;
       #10;
       StartTx = 1'b0;
       #2000;
       
     end
  
    initial begin
        $dumpfile("dump.vcd");
      	$dumpvars;
        #4000;
        $finish();
    end
endmodule

Modules/SerialTranceiver/SerialTrasceiver/SerialTrasceiver.sim/sim_1/behav/xsim/dump.vcd
$date
   Sat Jan 27 23:04:03 2024
$end
$version
  2022.2.2
$end
$timescale
  1ps
$end
$scope module tb_SerialTransciever $end
$var reg 32 ! DataIn [31:0] $end
$var reg 1 " Sample $end
$var reg 1 # StartTx $end
$var reg 1 $ Reset $end
$var reg 1 % Clk $end
$var reg 1 & ClkTx $end
$var wire 1 ' TxDone $end
$var wire 1 ( TxBusy $end
$var wire 1 ) Dout $end
$scope module dut $end
$var wire 32 * DataIn [31:0] $end
$var wire 1 + Sample $end
$var wire 1 , StartTx $end
$var wire 1 - Reset $end
$var wire 1 . Clk $end
$var wire 1 / ClkTx $end
$var reg 1 0 TxDone $end
$var reg 1 1 TxBusy $end
$var reg 1 2 Dout $end
$var reg 32 3 InternRegister [31:0] $end
$var reg 32 4 Count_bits [31:0] $end
$var reg 1 5 TxBusyIntern $end
$scope task ResetValues $end
$upscope $end
$upscope $end
$upscope $end
$enddefinitions $end
#0
$dumpvars
bx !
0"
0#
1$
0%
0&
x'
0(
0)
bx *
0+
0,
1-
0.
0/
x0
01
02
b0 3
b0 4
05
$end
#5000
1%
1.
01
02
b0 3
b0 4
05
#8000
0$
0-
#10000
0%
0.
#15000
1%
1&
0'
1.
1/
00
#18000
b11111111001000100011001101000101 !
1"
b11111111001000100011001101000101 *
1+
#20000
0%
0.
#25000
1%
1.
00
b11111111001000100011001101000101 3
#30000
0%
0&
0.
0/
#35000
1%
1.
00
b11111111001000100011001101000101 3
#38000
0"
1#
0+
1,
#40000
0%
0.
#45000
1%
1&
1.
1/
00
15
#50000
0%
0.
#55000
1%
1.
00
15
#60000
0%
0&
0.
0/
#65000
1%
1.
00
15
#70000
0%
0.
#75000
1%
1&
1(
1)
1.
1/
00
11
12
b11111110010001000110011010001010 3
b1 4
15
#80000
0%
0.
#85000
1%
1.
00
15
#88000
0#
0,
#90000
0%
0&
0.
0/
#95000
1%
1.
00
#100000
0%
0.
#105000
1%
1&
1.
1/
00
11
12
b11111100100010001100110100010100 3
b10 4
#108000
b10000100010001 !
1"
b10000100010001 *
1+
#110000
0%
0.
#115000
1%
1.
00
b11111100100010001100110100010100 3
#118000
0"
0+
#120000
0%
0&
0.
0/
#125000
1%
1.
00
#130000
0%
0.
#135000
1%
1&
1.
1/
00
11
12
b11111001000100011001101000101000 3
b11 4
#140000
0%
0.
#145000
1%
1.
00
#150000
0%
0&
0.
0/
#155000
1%
1.
00
#160000
0%
0.
#165000
1%
1&
1.
1/
00
11
12
b11110010001000110011010001010000 3
b100 4
#170000
0%
0.
#175000
1%
1.
00
#180000
0%
0&
0.
0/
#185000
1%
1.
00
#190000
0%
0.
#195000
1%
1&
1.
1/
00
11
12
b11100100010001100110100010100000 3
b101 4
#200000
0%
0.
#205000
1%
1.
00
#210000
0%
0&
0.
0/
#215000
1%
1.
00
#220000
0%
0.
#225000
1%
1&
1.
1/
00
11
12
b11001000100011001101000101000000 3
b110 4
#230000
0%
0.
#235000
1%
1.
00
#240000
0%
0&
0.
0/
#245000
1%
1.
00
#250000
0%
0.
#255000
1%
1&
1.
1/
00
11
12
b10010001000110011010001010000000 3
b111 4
#260000
0%
0.
#265000
1%
1.
00
#270000
0%
0&
0.
0/
#275000
1%
1.
00
#280000
0%
0.
#285000
1%
1&
1.
1/
00
11
12
b100010001100110100010100000000 3
b1000 4
#290000
0%
0.
#295000
1%
1.
00
#300000
0%
0&
0.
0/
#305000
1%
1.
00
#310000
0%
0.
#315000
1%
1&
0)
1.
1/
00
11
02
b1000100011001101000101000000000 3
b1001 4
#320000
0%
0.
#325000
1%
1.
00
#330000
0%
0&
0.
0/
#335000
1%
1.
00
#340000
0%
0.
#345000
1%
1&
1.
1/
00
11
02
b10001000110011010001010000000000 3
b1010 4
#350000
0%
0.
#355000
1%
1.
00
#360000
0%
0&
0.
0/
#365000
1%
1.
00
#370000
0%
0.
#375000
1%
1&
1)
1.
1/
00
11
12
b10001100110100010100000000000 3
b1011 4
#380000
0%
0.
#385000
1%
1.
00
#390000
0%
0&
0.
0/
#395000
1%
1.
00
#400000
0%
0.
#405000
1%
1&
0)
1.
1/
00
11
02
b100011001101000101000000000000 3
b1100 4
#410000
0%
0.
#415000
1%
1.
00
#420000
0%
0&
0.
0/
#425000
1%
1.
00
#430000
0%
0.
#435000
1%
1&
1.
1/
00
11
02
b1000110011010001010000000000000 3
b1101 4
#440000
0%
0.
#445000
1%
1.
00
#450000
0%
0&
0.
0/
#455000
1%
1.
00
#460000
0%
0.
#465000
1%
1&
1.
1/
00
11
02
b10001100110100010100000000000000 3
b1110 4
#470000
0%
0.
#475000
1%
1.
00
#480000
0%
0&
0.
0/
#485000
1%
1.
00
#490000
0%
0.
#495000
1%
1&
1)
1.
1/
00
11
12
b11001101000101000000000000000 3
b1111 4
#500000
0%
0.
#505000
1%
1.
00
#510000
0%
0&
0.
0/
#515000
1%
1.
00
#520000
0%
0.
#525000
1%
1&
0)
1.
1/
00
11
02
b110011010001010000000000000000 3
b10000 4
#530000
0%
0.
#535000
1%
1.
00
#540000
0%
0&
0.
0/
#545000
1%
1.
00
#550000
0%
0.
#555000
1%
1&
1.
1/
00
11
02
b1100110100010100000000000000000 3
b10001 4
#560000
0%
0.
#565000
1%
1.
00
#570000
0%
0&
0.
0/
#575000
1%
1.
00
#580000
0%
0.
#585000
1%
1&
1.
1/
00
11
02
b11001101000101000000000000000000 3
b10010 4
#590000
0%
0.
#595000
1%
1.
00
#600000
0%
0&
0.
0/
#605000
1%
1.
00
#610000
0%
0.
#615000
1%
1&
1)
1.
1/
00
11
12
b10011010001010000000000000000000 3
b10011 4
#618000
1$
0(
0)
1-
01
02
b0 3
b0 4
05
#620000
0%
0.
#625000
1%
1.
01
02
b0 3
b0 4
05
#630000
0%
0&
0.
0/
#631000
b11110010010110011111110100011011 !
0$
b11110010010110011111110100011011 *
0-
#635000
1%
1.
00
#640000
0%
0.
#641000
1"
1+
#645000
1%
1&
1.
1/
00
b11110010010110011111110100011011 3
#650000
0%
0.
#653000
0"
0+
#655000
1%
1.
00
#658000
1#
1,
#660000
0%
0&
0.
0/
#665000
1%
1.
00
15
#668000
0#
0,
#670000
0%
0.
#675000
1%
1&
1(
1)
1.
1/
00
11
12
b11100100101100111111101000110110 3
b1 4
#680000
0%
0.
#685000
1%
1.
00
#690000
0%
0&
0.
0/
#695000
1%
1.
00
#700000
0%
0.
#705000
1%
1&
1.
1/
00
11
12
b11001001011001111111010001101100 3
b10 4
#710000
0%
0.
#715000
1%
1.
00
#720000
0%
0&
0.
0/
#725000
1%
1.
00
#730000
0%
0.
#735000
1%
1&
1.
1/
00
11
12
b10010010110011111110100011011000 3
b11 4
#740000
0%
0.
#745000
1%
1.
00
#750000
0%
0&
0.
0/
#755000
1%
1.
00
#760000
0%
0.
#765000
1%
1&
1.
1/
00
11
12
b100101100111111101000110110000 3
b100 4
#770000
0%
0.
#775000
1%
1.
00
#780000
0%
0&
0.
0/
#785000
1%
1.
00
#790000
0%
0.
#795000
1%
1&
0)
1.
1/
00
11
02
b1001011001111111010001101100000 3
b101 4
#800000
0%
0.
#805000
1%
1.
00
#810000
0%
0&
0.
0/
#815000
1%
1.
00
#820000
0%
0.
#825000
1%
1&
1.
1/
00
11
02
b10010110011111110100011011000000 3
b110 4
#830000
0%
0.
#835000
1%
1.
00
#840000
0%
0&
0.
0/
#845000
1%
1.
00
#850000
0%
0.
#855000
1%
1&
1)
1.
1/
00
11
12
b101100111111101000110110000000 3
b111 4
#860000
0%
0.
#865000
1%
1.
00
#870000
0%
0&
0.
0/
#875000
1%
1.
00
#880000
0%
0.
#885000
1%
1&
0)
1.
1/
00
11
02
b1011001111111010001101100000000 3
b1000 4
#890000
0%
0.
#895000
1%
1.
00
#900000
0%
0&
0.
0/
#905000
1%
1.
00
#910000
0%
0.
#915000
1%
1&
1.
1/
00
11
02
b10110011111110100011011000000000 3
b1001 4
#920000
0%
0.
#925000
1%
1.
00
#930000
0%
0&
0.
0/
#935000
1%
1.
00
#940000
0%
0.
#945000
1%
1&
1)
1.
1/
00
11
12
b1100111111101000110110000000000 3
b1010 4
#950000
0%
0.
#955000
1%
1.
00
#960000
0%
0&
0.
0/
#965000
1%
1.
00
#970000
0%
0.
#975000
1%
1&
0)
1.
1/
00
11
02
b11001111111010001101100000000000 3
b1011 4
#980000
0%
0.
#985000
1%
1.
00
#990000
0%
0&
0.
0/
#995000
1%
1.
00
#1000000
0%
0.
#1005000
1%
1&
1)
1.
1/
00
11
12
b10011111110100011011000000000000 3
b1100 4
#1010000
0%
0.
#1015000
1%
1.
00
#1020000
0%
0&
0.
0/
#1025000
1%
1.
00
#1030000
0%
0.
#1035000
1%
1&
1.
1/
00
11
12
b111111101000110110000000000000 3
b1101 4
#1040000
0%
0.
#1045000
1%
1.
00
#1050000
0%
0&
0.
0/
#1055000
1%
1.
00
#1060000
0%
0.
#1065000
1%
1&
0)
1.
1/
00
11
02
b1111111010001101100000000000000 3
b1110 4
#1070000
0%
0.
#1075000
1%
1.
00
#1080000
0%
0&
0.
0/
#1085000
1%
1.
00
#1090000
0%
0.
#1095000
1%
1&
1.
1/
00
11
02
b11111110100011011000000000000000 3
b1111 4
#1100000
0%
0.
#1105000
1%
1.
00
#1110000
0%
0&
0.
0/
#1115000
1%
1.
00
#1120000
0%
0.
#1125000
1%
1&
1)
1.
1/
00
11
12
b11111101000110110000000000000000 3
b10000 4
#1130000
0%
0.
#1135000
1%
1.
00
#1140000
0%
0&
0.
0/
#1145000
1%
1.
00
#1150000
0%
0.
#1155000
1%
1&
1.
1/
00
11
12
b11111010001101100000000000000000 3
b10001 4
#1160000
0%
0.
#1165000
1%
1.
00
#1170000
0%
0&
0.
0/
#1175000
1%
1.
00
#1180000
0%
0.
#1185000
1%
1&
1.
1/
00
11
12
b11110100011011000000000000000000 3
b10010 4
#1190000
0%
0.
#1195000
1%
1.
00
#1200000
0%
0&
0.
0/
#1205000
1%
1.
00
#1210000
0%
0.
#1215000
1%
1&
1.
1/
00
11
12
b11101000110110000000000000000000 3
b10011 4
#1220000
0%
0.
#1225000
1%
1.
00
#1230000
0%
0&
0.
0/
#1235000
1%
1.
00
#1240000
0%
0.
#1245000
1%
1&
1.
1/
00
11
12
b11010001101100000000000000000000 3
b10100 4
#1250000
0%
0.
#1255000
1%
1.
00
#1260000
0%
0&
0.
0/
#1265000
1%
1.
00
#1270000
0%
0.
#1275000
1%
1&
1.
1/
00
11
12
b10100011011000000000000000000000 3
b10101 4
#1280000
0%
0.
#1285000
1%
1.
00
#1290000
0%
0&
0.
0/
#1295000
1%
1.
00
#1300000
0%
0.
#1305000
1%
1&
1.
1/
00
11
12
b1000110110000000000000000000000 3
b10110 4
#1310000
0%
0.
#1315000
1%
1.
00
#1320000
0%
0&
0.
0/
#1325000
1%
1.
00
#1330000
0%
0.
#1335000
1%
1&
0)
1.
1/
00
11
02
b10001101100000000000000000000000 3
b10111 4
#1340000
0%
0.
#1345000
1%
1.
00
#1350000
0%
0&
0.
0/
#1355000
1%
1.
00
#1360000
0%
0.
#1365000
1%
1&
1)
1.
1/
00
11
12
b11011000000000000000000000000 3
b11000 4
#1370000
0%
0.
#1375000
1%
1.
00
#1380000
0%
0&
0.
0/
#1385000
1%
1.
00
#1390000
0%
0.
#1395000
1%
1&
0)
1.
1/
00
11
02
b110110000000000000000000000000 3
b11001 4
#1400000
0%
0.
#1405000
1%
1.
00
#1410000
0%
0&
0.
0/
#1415000
1%
1.
00
#1420000
0%
0.
#1425000
1%
1&
1.
1/
00
11
02
b1101100000000000000000000000000 3
b11010 4
#1430000
0%
0.
#1435000
1%
1.
00
#1440000
0%
0&
0.
0/
#1445000
1%
1.
00
#1450000
0%
0.
#1455000
1%
1&
1.
1/
00
11
02
b11011000000000000000000000000000 3
b11011 4
#1460000
0%
0.
#1465000
1%
1.
00
#1470000
0%
0&
0.
0/
#1475000
1%
1.
00
#1480000
0%
0.
#1485000
1%
1&
1)
1.
1/
00
11
12
b10110000000000000000000000000000 3
b11100 4
#1490000
0%
0.
#1495000
1%
1.
00
#1500000
0%
0&
0.
0/
#1505000
1%
1.
00
#1510000
0%
0.
#1515000
1%
1&
1.
1/
00
11
12
b1100000000000000000000000000000 3
b11101 4
#1520000
0%
0.
#1525000
1%
1.
00
#1530000
0%
0&
0.
0/
#1535000
1%
1.
00
#1540000
0%
0.
#1545000
1%
1&
0)
1.
1/
00
11
02
b11000000000000000000000000000000 3
b11110 4
#1550000
0%
0.
#1555000
1%
1.
00
#1560000
0%
0&
0.
0/
#1565000
1%
1.
00
#1570000
0%
0.
#1575000
1%
1&
1)
1.
1/
00
11
12
b10000000000000000000000000000000 3
b11111 4
#1580000
0%
0.
#1585000
1%
1.
00
#1590000
0%
0&
0.
0/
#1595000
1%
1.
00
#1600000
0%
0.
#1605000
1%
1&
1.
1/
00
11
12
b0 3
b100000 4
#1610000
0%
0.
#1615000
1%
1.
00
#1620000
0%
0&
0.
0/
#1625000
1%
1.
00
#1630000
0%
0.
#1635000
1%
1&
1'
0(
0)
1.
1/
10
01
02
b0 3
b0 4
05
#1640000
0%
0.
#1645000
1%
0'
1.
00
#1650000
0%
0&
0.
0/
#1655000
1%
1.
00
#1660000
0%
0.
#1665000
1%
1&
1.
1/
00
#1670000
0%
0.
#1675000
1%
1.
00
#1680000
0%
0&
0.
0/
#1685000
1%
1.
00
#1690000
0%
0.
#1695000
1%
1&
1.
1/
00
#1700000
0%
0.
#1705000
1%
1.
00
#1710000
0%
0&
0.
0/
#1715000
1%
1.
00
#1720000
0%
0.
#1725000
1%
1&
1.
1/
00
#1730000
0%
0.
#1735000
1%
1.
00
#1740000
0%
0&
0.
0/
#1745000
1%
1.
00
#1750000
0%
0.
#1755000
1%
1&
1.
1/
00
#1760000
0%
0.
#1765000
1%
1.
00
#1770000
0%
0&
0.
0/
#1775000
1%
1.
00
#1780000
0%
0.
#1785000
1%
1&
1.
1/
00
#1790000
0%
0.
#1795000
1%
1.
00
#1800000
0%
0&
0.
0/
#1805000
1%
1.
00
#1810000
0%
0.
#1815000
1%
1&
1.
1/
00
#1820000
0%
0.
#1825000
1%
1.
00
#1830000
0%
0&
0.
0/
#1835000
1%
1.
00
#1840000
0%
0.
#1845000
1%
1&
1.
1/
00
#1850000
0%
0.
#1855000
1%
1.
00
#1860000
0%
0&
0.
0/
#1865000
1%
1.
00
#1870000
0%
0.
#1875000
1%
1&
1.
1/
00
#1880000
0%
0.
#1885000
1%
1.
00
#1890000
0%
0&
0.
0/
#1895000
1%
1.
00
#1900000
0%
0.
#1905000
1%
1&
1.
1/
00
#1910000
0%
0.
#1915000
1%
1.
00
#1920000
0%
0&
0.
0/
#1925000
1%
1.
00
#1930000
0%
0.
#1935000
1%
1&
1.
1/
00
#1940000
0%
0.
#1945000
1%
1.
00
#1950000
0%
0&
0.
0/
#1955000
1%
1.
00
#1960000
0%
0.
#1965000
1%
1&
1.
1/
00
#1970000
0%
0.
#1975000
1%
1.
00
#1980000
0%
0&
0.
0/
#1985000
1%
1.
00
#1990000
0%
0.
#1995000
1%
1&
1.
1/
00
